{"version":"https://jsonfeed.org/version/1","title":"Hacks by  Coding Blog By Arnab Kumar Shil","description":"Technical blogs by Arnab Kumar Shil,  @  https://ruddra.com/","home_page_url":"https://ruddra.com","feed_url":"https://ruddra.com/tags/csv/index.json","author":{"name":"Arnab Kumar Shil","url":"https://ruddra.com","avatar":"https://ruddra.com/avatar.jpg"},"item":{"date_published":"2016-01-10T15:21:42Z","date_modified":"2020-06-26T10:22:21+06:00","id":"https://ruddra.com/tags/csv/","url":"https://ruddra.com/tags/csv/","title":"CSV","image":"https://ruddra.com","content_html":"","content":""}}